rechat/__init__.py
rechat/admin.py
rechat/apps.py
rechat/hook.py
rechat/models.py
rechat/producers.py
rechat/signals.py
rechat/urls.py
rechat/views.py
rechat/migrations/0001_initial.py
rechat/migrations/__init__.py
rechat/static/rechat/index.js
rechat/templates/rechat/init.html
rechat/templates/rechat/message.html
rechat/templates/rechat/room.html
rechat/templates/rechat/rooms.html
django_rechat-0.2.0.dist-info/LICENSE
django_rechat-0.2.0.dist-info/METADATA
django_rechat-0.2.0.dist-info/WHEEL
django_rechat-0.2.0.dist-info/top_level.txt
django_rechat-0.2.0.dist-info/RECORD
