Metadata-Version: 2.1
Name: django-rechat
Version: 0.2.0
Summary: A chat application for Django
Home-page: https://github.com/synw/django-rechat
Download-URL: https://github.com/synw/django-rechat/releases/tag/0.2.0
Author: synw
Author-email: synwe@yahoo.com
License: UNKNOWN
Keywords: django,chat,websockets
Platform: UNKNOWN
Classifier: Development Status :: 4 - Beta
Classifier: Framework :: Django :: 1.11
Classifier: Intended Audience :: Developers
Classifier: License :: OSI Approved :: MIT License
Classifier: Programming Language :: Python :: 3.8
License-File: LICENSE
Requires-Dist: django-instant
